{
  "frequency": 20,
  "countdown": 3,
  "timestamp": "2025-01-21T10:49:25.000008",
  "joint_name_to_id": {
    "left_shoulder_yaw": 11,
    "left_shoulder_pitch": 12,
    "left_elbow_yaw": 13,
    "left_gripper": 14,
    "right_shoulder_yaw": 21,
    "right_shoulder_pitch": 22,
    "right_elbow_yaw": 23,
    "right_gripper": 24,
    "left_hip_yaw": 31,
    "left_hip_roll": 32,
    "left_hip_pitch": 33,
    "left_knee_pitch": 34,
    "left_ankle_pitch": 35,
    "right_hip_yaw": 41,
    "right_hip_roll": 42,
    "right_hip_pitch": 43,
    "right_knee_pitch": 44,
    "right_ankle_pitch": 45
  },
  "frames": [
    {
      "left_shoulder_yaw": -3.603515625,
      "left_shoulder_pitch": 78.837890625,
      "left_elbow_yaw": -0.703125,
      "left_gripper": -0.087890625,
      "right_shoulder_yaw": 0.17578125,
      "right_shoulder_pitch": -71.54296875,
      "right_elbow_yaw": 0.087890625,
      "right_gripper": -0.17578125,
      "left_hip_yaw": -11.6015625,
      "left_hip_roll": 18.80859375,
      "left_hip_pitch": -39.814453125,
      "left_knee_pitch": 45.0,
      "left_ankle_pitch": 12.041015625,
      "right_hip_yaw": 9.228515625,
      "right_hip_roll": 0.17578125,
      "right_hip_pitch": 26.71875,
      "right_knee_pitch": -38.3203125,
      "right_ankle_pitch": -12.041015625
    },
    {
      "left_shoulder_yaw": -3.603515625,
      "left_shoulder_pitch": 78.837890625,
      "left_elbow_yaw": -0.703125,
      "left_gripper": -0.087890625,
      "right_shoulder_yaw": 0.17578125,
      "right_shoulder_pitch": -71.54296875,
      "right_elbow_yaw": 0.087890625,
      "right_gripper": -0.17578125,
      "left_hip_yaw": -11.6015625,
      "left_hip_roll": 18.80859375,
      "left_hip_pitch": -39.814453125,
      "left_knee_pitch": 45.0,
      "left_ankle_pitch": 12.041015625,
      "right_hip_yaw": 9.228515625,
      "right_hip_roll": 0.17578125,
      "right_hip_pitch": 26.71875,
      "right_knee_pitch": -38.3203125,
      "right_ankle_pitch": -12.041015625
    },
    {
      "left_shoulder_yaw": -3.603515625,
      "left_shoulder_pitch": 78.837890625,
      "left_elbow_yaw": -0.703125,
      "left_gripper": -0.087890625,
      "right_shoulder_yaw": 0.17578125,
      "right_shoulder_pitch": -71.54296875,
      "right_elbow_yaw": 0.087890625,
      "right_gripper": -0.17578125,
      "left_hip_yaw": -11.6015625,
      "left_hip_roll": 18.80859375,
      "left_hip_pitch": -39.814453125,
      "left_knee_pitch": 45.0,
      "left_ankle_pitch": 12.041015625,
      "right_hip_yaw": 9.228515625,
      "right_hip_roll": 0.17578125,
      "right_hip_pitch": 26.71875,
      "right_knee_pitch": -38.3203125,
      "right_ankle_pitch": -12.041015625
    },
    {
      "left_shoulder_yaw": -3.603515625,
      "left_shoulder_pitch": 78.837890625,
      "left_elbow_yaw": -0.703125,
      "left_gripper": -0.087890625,
      "right_shoulder_yaw": 0.17578125,
      "right_shoulder_pitch": -71.54296875,
      "right_elbow_yaw": 0.087890625,
      "right_gripper": -0.17578125,
      "left_hip_yaw": -11.6015625,
      "left_hip_roll": 18.80859375,
      "left_hip_pitch": -39.814453125,
      "left_knee_pitch": 45.0,
      "left_ankle_pitch": 12.041015625,
      "right_hip_yaw": 9.228515625,
      "right_hip_roll": 0.17578125,
      "right_hip_pitch": 26.71875,
      "right_knee_pitch": -38.3203125,
      "right_ankle_pitch": -12.041015625
    },
    {
      "left_shoulder_yaw": -3.603515625,
      "left_shoulder_pitch": 78.837890625,
      "left_elbow_yaw": -0.703125,
      "left_gripper": -0.087890625,
      "right_shoulder_yaw": 0.17578125,
      "right_shoulder_pitch": -71.54296875,
      "right_elbow_yaw": 0.087890625,
      "right_gripper": -0.17578125,
      "left_hip_yaw": -11.6015625,
      "left_hip_roll": 18.80859375,
      "left_hip_pitch": -39.90234375,
      "left_knee_pitch": 45.0,
      "left_ankle_pitch": 12.12890625,
      "right_hip_yaw": 9.228515625,
      "right_hip_roll": 0.17578125,
      "right_hip_pitch": 26.71875,
      "right_knee_pitch": -38.3203125,
      "right_ankle_pitch": -12.041015625
    },
    {
      "left_shoulder_yaw": -3.603515625,
      "left_shoulder_pitch": 78.837890625,
      "left_elbow_yaw": -0.703125,
      "left_gripper": -0.087890625,
      "right_shoulder_yaw": 0.17578125,
      "right_shoulder_pitch": -71.54296875,
      "right_elbow_yaw": 0.087890625,
      "right_gripper": -0.17578125,
      "left_hip_yaw": -11.6015625,
      "left_hip_roll": 18.80859375,
      "left_hip_pitch": -39.990234375,
      "left_knee_pitch": 45.0,
      "left_ankle_pitch": 12.12890625,
      "right_hip_yaw": 9.228515625,
      "right_hip_roll": 0.17578125,
      "right_hip_pitch": 26.71875,
      "right_knee_pitch": -38.3203125,
      "right_ankle_pitch": -12.041015625
    },
    {
      "left_shoulder_yaw": -3.603515625,
      "left_shoulder_pitch": 78.837890625,
      "left_elbow_yaw": -0.703125,
      "left_gripper": -0.087890625,
      "right_shoulder_yaw": 0.17578125,
      "right_shoulder_pitch": -71.54296875,
      "right_elbow_yaw": 0.087890625,
      "right_gripper": -0.17578125,
      "left_hip_yaw": -11.6015625,
      "left_hip_roll": 18.80859375,
      "left_hip_pitch": -40.166015625,
      "left_knee_pitch": 45.0,
      "left_ankle_pitch": 12.12890625,
      "right_hip_yaw": 9.228515625,
      "right_hip_roll": 0.17578125,
      "right_hip_pitch": 26.71875,
      "right_knee_pitch": -38.3203125,
      "right_ankle_pitch": -12.041015625
    },
    {
      "left_shoulder_yaw": -3.603515625,
      "left_shoulder_pitch": 78.837890625,
      "left_elbow_yaw": -0.703125,
      "left_gripper": -0.087890625,
      "right_shoulder_yaw": 0.17578125,
      "right_shoulder_pitch": -71.54296875,
      "right_elbow_yaw": 0.087890625,
      "right_gripper": -0.17578125,
      "left_hip_yaw": -11.6015625,
      "left_hip_roll": 18.80859375,
      "left_hip_pitch": -40.166015625,
      "left_knee_pitch": 45.0,
      "left_ankle_pitch": 12.12890625,
      "right_hip_yaw": 9.228515625,
      "right_hip_roll": 0.17578125,
      "right_hip_pitch": 26.806640625,
      "right_knee_pitch": -38.3203125,
      "right_ankle_pitch": -12.041015625
    },
    {
      "left_shoulder_yaw": -3.603515625,
      "left_shoulder_pitch": 78.837890625,
      "left_elbow_yaw": -0.703125,
      "left_gripper": -0.087890625,
      "right_shoulder_yaw": 0.17578125,
      "right_shoulder_pitch": -71.54296875,
      "right_elbow_yaw": 0.087890625,
      "right_gripper": -0.17578125,
      "left_hip_yaw": -11.6015625,
      "left_hip_roll": 18.80859375,
      "left_hip_pitch": -40.166015625,
      "left_knee_pitch": 45.0,
      "left_ankle_pitch": 12.12890625,
      "right_hip_yaw": 9.228515625,
      "right_hip_roll": 0.17578125,
      "right_hip_pitch": 26.806640625,
      "right_knee_pitch": -38.3203125,
      "right_ankle_pitch": -12.041015625
    },
    {
      "left_shoulder_yaw": -3.603515625,
      "left_shoulder_pitch": 78.837890625,
      "left_elbow_yaw": -0.703125,
      "left_gripper": -0.087890625,
      "right_shoulder_yaw": 0.17578125,
      "right_shoulder_pitch": -71.54296875,
      "right_elbow_yaw": 0.087890625,
      "right_gripper": -0.17578125,
      "left_hip_yaw": -11.6015625,
      "left_hip_roll": 18.80859375,
      "left_hip_pitch": -40.166015625,
      "left_knee_pitch": 45.087890625,
      "left_ankle_pitch": 12.12890625,
      "right_hip_yaw": 9.228515625,
      "right_hip_roll": 0.17578125,
      "right_hip_pitch": 26.806640625,
      "right_knee_pitch": -38.3203125,
      "right_ankle_pitch": -12.041015625
    },
    {
      "left_shoulder_yaw": -3.603515625,
      "left_shoulder_pitch": 78.837890625,
      "left_elbow_yaw": -0.703125,
      "left_gripper": -0.087890625,
      "right_shoulder_yaw": 0.17578125,
      "right_shoulder_pitch": -71.54296875,
      "right_elbow_yaw": 0.087890625,
      "right_gripper": -0.17578125,
      "left_hip_yaw": -11.6015625,
      "left_hip_roll": 18.80859375,
      "left_hip_pitch": -40.25390625,
      "left_knee_pitch": 45.087890625,
      "left_ankle_pitch": 12.12890625,
      "right_hip_yaw": 9.228515625,
      "right_hip_roll": 0.17578125,
      "right_hip_pitch": 26.806640625,
      "right_knee_pitch": -38.3203125,
      "right_ankle_pitch": -12.041015625
    },
    {
      "left_shoulder_yaw": -3.603515625,
      "left_shoulder_pitch": 78.837890625,
      "left_elbow_yaw": -0.703125,
      "left_gripper": -0.087890625,
      "right_shoulder_yaw": 0.17578125,
      "right_shoulder_pitch": -71.54296875,
      "right_elbow_yaw": 0.087890625,
      "right_gripper": -0.17578125,
      "left_hip_yaw": -11.6015625,
      "left_hip_roll": 18.80859375,
      "left_hip_pitch": -40.25390625,
      "left_knee_pitch": 45.087890625,
      "left_ankle_pitch": 12.12890625,
      "right_hip_yaw": 9.228515625,
      "right_hip_roll": 0.17578125,
      "right_hip_pitch": 26.806640625,
      "right_knee_pitch": -38.3203125,
      "right_ankle_pitch": -12.041015625
    },
    {
      "left_shoulder_yaw": -3.603515625,
      "left_shoulder_pitch": 78.837890625,
      "left_elbow_yaw": -0.52734375,
      "left_gripper": -0.087890625,
      "right_shoulder_yaw": 0.17578125,
      "right_shoulder_pitch": -71.54296875,
      "right_elbow_yaw": 0.087890625,
      "right_gripper": -0.17578125,
      "left_hip_yaw": -11.6015625,
      "left_hip_roll": 18.80859375,
      "left_hip_pitch": -40.25390625,
      "left_knee_pitch": 45.17578125,
      "left_ankle_pitch": 12.12890625,
      "right_hip_yaw": 9.228515625,
      "right_hip_roll": 0.17578125,
      "right_hip_pitch": 26.71875,
      "right_knee_pitch": -38.3203125,
      "right_ankle_pitch": -12.041015625
    },
    {
      "left_shoulder_yaw": -3.603515625,
      "left_shoulder_pitch": 78.837890625,
      "left_elbow_yaw": -0.615234375,
      "left_gripper": -0.087890625,
      "right_shoulder_yaw": 0.17578125,
      "right_shoulder_pitch": -71.54296875,
      "right_elbow_yaw": 0.087890625,
      "right_gripper": -0.17578125,
      "left_hip_yaw": -11.6015625,
      "left_hip_roll": 18.80859375,
      "left_hip_pitch": -40.25390625,
      "left_knee_pitch": 45.263671875,
      "left_ankle_pitch": 12.216796875,
      "right_hip_yaw": 9.228515625,
      "right_hip_roll": 0.17578125,
      "right_hip_pitch": 26.71875,
      "right_knee_pitch": -38.3203125,
      "right_ankle_pitch": -12.041015625
    },
    {
      "left_shoulder_yaw": -3.603515625,
      "left_shoulder_pitch": 78.837890625,
      "left_elbow_yaw": -0.703125,
      "left_gripper": -0.087890625,
      "right_shoulder_yaw": 0.17578125,
      "right_shoulder_pitch": -71.54296875,
      "right_elbow_yaw": 0.087890625,
      "right_gripper": -0.17578125,
      "left_hip_yaw": -11.6015625,
      "left_hip_roll": 18.80859375,
      "left_hip_pitch": -40.25390625,
      "left_knee_pitch": 45.263671875,
      "left_ankle_pitch": 12.216796875,
      "right_hip_yaw": 9.228515625,
      "right_hip_roll": 0.17578125,
      "right_hip_pitch": 26.71875,
      "right_knee_pitch": -38.3203125,
      "right_ankle_pitch": -12.12890625
    },
    {
      "left_shoulder_yaw": -3.603515625,
      "left_shoulder_pitch": 78.837890625,
      "left_elbow_yaw": -0.703125,
      "left_gripper": -0.087890625,
      "right_shoulder_yaw": 0.17578125,
      "right_shoulder_pitch": -71.54296875,
      "right_elbow_yaw": 0.087890625,
      "right_gripper": -0.17578125,
      "left_hip_yaw": -11.6015625,
      "left_hip_roll": 18.80859375,
      "left_hip_pitch": -40.341796875,
      "left_knee_pitch": 46.0546875,
      "left_ankle_pitch": 12.392578125,
      "right_hip_yaw": 9.228515625,
      "right_hip_roll": 0.17578125,
      "right_hip_pitch": 26.71875,
      "right_knee_pitch": -38.408203125,
      "right_ankle_pitch": -12.12890625
    },
    {
      "left_shoulder_yaw": -3.603515625,
      "left_shoulder_pitch": 78.837890625,
      "left_elbow_yaw": -0.703125,
      "left_gripper": -0.087890625,
      "right_shoulder_yaw": 0.17578125,
      "right_shoulder_pitch": -71.455078125,
      "right_elbow_yaw": 0.087890625,
      "right_gripper": -0.17578125,
      "left_hip_yaw": -11.6015625,
      "left_hip_roll": 18.80859375,
      "left_hip_pitch": -40.517578125,
      "left_knee_pitch": 48.1640625,
      "left_ankle_pitch": 13.0078125,
      "right_hip_yaw": 9.140625,
      "right_hip_roll": 0.17578125,
      "right_hip_pitch": 26.630859375,
      "right_knee_pitch": -38.671875,
      "right_ankle_pitch": -12.48046875
    },
    {
      "left_shoulder_yaw": -3.603515625,
      "left_shoulder_pitch": 78.22265625,
      "left_elbow_yaw": -0.52734375,
      "left_gripper": -0.087890625,
      "right_shoulder_yaw": 0.17578125,
      "right_shoulder_pitch": -70.751953125,
      "right_elbow_yaw": 0.087890625,
      "right_gripper": -0.17578125,
      "left_hip_yaw": -11.689453125,
      "left_hip_roll": 18.80859375,
      "left_hip_pitch": -40.517578125,
      "left_knee_pitch": 49.658203125,
      "left_ankle_pitch": 13.18359375,
      "right_hip_yaw": 9.140625,
      "right_hip_roll": 0.17578125,
      "right_hip_pitch": 26.455078125,
      "right_knee_pitch": -38.671875,
      "right_ankle_pitch": -13.623046875
    },
    {
      "left_shoulder_yaw": -3.603515625,
      "left_shoulder_pitch": 78.75,
      "left_elbow_yaw": -0.52734375,
      "left_gripper": -0.087890625,
      "right_shoulder_yaw": 0.17578125,
      "right_shoulder_pitch": -71.103515625,
      "right_elbow_yaw": 0.087890625,
      "right_gripper": -0.17578125,
      "left_hip_yaw": -11.689453125,
      "left_hip_roll": 18.80859375,
      "left_hip_pitch": -40.517578125,
      "left_knee_pitch": 48.779296875,
      "left_ankle_pitch": 13.095703125,
      "right_hip_yaw": 9.140625,
      "right_hip_roll": 0.17578125,
      "right_hip_pitch": 26.54296875,
      "right_knee_pitch": -38.759765625,
      "right_ankle_pitch": -13.7109375
    },
    {
      "left_shoulder_yaw": -3.603515625,
      "left_shoulder_pitch": 78.75,
      "left_elbow_yaw": -0.52734375,
      "left_gripper": -0.087890625,
      "right_shoulder_yaw": 0.17578125,
      "right_shoulder_pitch": -71.279296875,
      "right_elbow_yaw": 0.087890625,
      "right_gripper": -0.17578125,
      "left_hip_yaw": -11.689453125,
      "left_hip_roll": 18.80859375,
      "left_hip_pitch": -40.25390625,
      "left_knee_pitch": 48.779296875,
      "left_ankle_pitch": 13.095703125,
      "right_hip_yaw": 9.140625,
      "right_hip_roll": 0.17578125,
      "right_hip_pitch": 26.3671875,
      "right_knee_pitch": -38.759765625,
      "right_ankle_pitch": -13.7109375
    },
    {
      "left_shoulder_yaw": -3.603515625,
      "left_shoulder_pitch": 78.75,
      "left_elbow_yaw": -0.791015625,
      "left_gripper": -0.087890625,
      "right_shoulder_yaw": 0.17578125,
      "right_shoulder_pitch": -71.3671875,
      "right_elbow_yaw": 0.087890625,
      "right_gripper": -0.17578125,
      "left_hip_yaw": -11.689453125,
      "left_hip_roll": 18.80859375,
      "left_hip_pitch": -39.814453125,
      "left_knee_pitch": 48.779296875,
      "left_ankle_pitch": 13.0078125,
      "right_hip_yaw": 9.140625,
      "right_hip_roll": 0.17578125,
      "right_hip_pitch": 26.19140625,
      "right_knee_pitch": -38.759765625,
      "right_ankle_pitch": -13.53515625
    },
    {
      "left_shoulder_yaw": -3.603515625,
      "left_shoulder_pitch": 78.75,
      "left_elbow_yaw": -0.966796875,
      "left_gripper": -0.087890625,
      "right_shoulder_yaw": 0.17578125,
      "right_shoulder_pitch": -71.455078125,
      "right_elbow_yaw": 0.087890625,
      "right_gripper": -0.17578125,
      "left_hip_yaw": -11.689453125,
      "left_hip_roll": 18.80859375,
      "left_hip_pitch": -39.7265625,
      "left_knee_pitch": 48.779296875,
      "left_ankle_pitch": 13.0078125,
      "right_hip_yaw": 9.140625,
      "right_hip_roll": 0.17578125,
      "right_hip_pitch": 26.455078125,
      "right_knee_pitch": -38.759765625,
      "right_ankle_pitch": -13.359375
    },
    {
      "left_shoulder_yaw": -3.603515625,
      "left_shoulder_pitch": 78.75,
      "left_elbow_yaw": -1.0546875,
      "left_gripper": -0.087890625,
      "right_shoulder_yaw": 0.17578125,
      "right_shoulder_pitch": -71.455078125,
      "right_elbow_yaw": 0.087890625,
      "right_gripper": -0.17578125,
      "left_hip_yaw": -11.689453125,
      "left_hip_roll": 18.80859375,
      "left_hip_pitch": -39.814453125,
      "left_knee_pitch": 48.779296875,
      "left_ankle_pitch": 13.0078125,
      "right_hip_yaw": 9.140625,
      "right_hip_roll": 0.17578125,
      "right_hip_pitch": 26.3671875,
      "right_knee_pitch": -38.759765625,
      "right_ankle_pitch": -13.359375
    },
    {
      "left_shoulder_yaw": -3.603515625,
      "left_shoulder_pitch": 78.75,
      "left_elbow_yaw": -1.318359375,
      "left_gripper": -0.087890625,
      "right_shoulder_yaw": 0.17578125,
      "right_shoulder_pitch": -71.455078125,
      "right_elbow_yaw": 0.087890625,
      "right_gripper": -0.17578125,
      "left_hip_yaw": -11.689453125,
      "left_hip_roll": 18.80859375,
      "left_hip_pitch": -39.990234375,
      "left_knee_pitch": 48.8671875,
      "left_ankle_pitch": 13.0078125,
      "right_hip_yaw": 9.140625,
      "right_hip_roll": 0.17578125,
      "right_hip_pitch": 26.3671875,
      "right_knee_pitch": -38.49609375,
      "right_ankle_pitch": -13.359375
    },
    {
      "left_shoulder_yaw": -3.603515625,
      "left_shoulder_pitch": 78.837890625,
      "left_elbow_yaw": -1.318359375,
      "left_gripper": -0.087890625,
      "right_shoulder_yaw": 0.17578125,
      "right_shoulder_pitch": -71.455078125,
      "right_elbow_yaw": 0.087890625,
      "right_gripper": -0.17578125,
      "left_hip_yaw": -11.689453125,
      "left_hip_roll": 18.80859375,
      "left_hip_pitch": -40.341796875,
      "left_knee_pitch": 49.130859375,
      "left_ankle_pitch": 13.0078125,
      "right_hip_yaw": 9.140625,
      "right_hip_roll": 0.17578125,
      "right_hip_pitch": 26.3671875,
      "right_knee_pitch": -38.49609375,
      "right_ankle_pitch": -13.359375
    },
    {
      "left_shoulder_yaw": -3.69140625,
      "left_shoulder_pitch": 78.837890625,
      "left_elbow_yaw": -1.0546875,
      "left_gripper": -0.087890625,
      "right_shoulder_yaw": 0.17578125,
      "right_shoulder_pitch": -71.630859375,
      "right_elbow_yaw": 0.087890625,
      "right_gripper": -0.17578125,
      "left_hip_yaw": -11.689453125,
      "left_hip_roll": 18.80859375,
      "left_hip_pitch": -40.517578125,
      "left_knee_pitch": 48.779296875,
      "left_ankle_pitch": 13.0078125,
      "right_hip_yaw": 9.140625,
      "right_hip_roll": 0.17578125,
      "right_hip_pitch": 26.455078125,
      "right_knee_pitch": -38.232421875,
      "right_ankle_pitch": -13.447265625
    },
    {
      "left_shoulder_yaw": -3.69140625,
      "left_shoulder_pitch": 78.837890625,
      "left_elbow_yaw": -1.0546875,
      "left_gripper": -0.087890625,
      "right_shoulder_yaw": 0.17578125,
      "right_shoulder_pitch": -71.54296875,
      "right_elbow_yaw": 0.087890625,
      "right_gripper": -0.17578125,
      "left_hip_yaw": -11.689453125,
      "left_hip_roll": 18.80859375,
      "left_hip_pitch": -40.517578125,
      "left_knee_pitch": 48.779296875,
      "left_ankle_pitch": 13.0078125,
      "right_hip_yaw": 9.140625,
      "right_hip_roll": 0.17578125,
      "right_hip_pitch": 26.455078125,
      "right_knee_pitch": -38.232421875,
      "right_ankle_pitch": -13.53515625
    },
    {
      "left_shoulder_yaw": -3.603515625,
      "left_shoulder_pitch": 78.837890625,
      "left_elbow_yaw": -0.791015625,
      "left_gripper": -0.087890625,
      "right_shoulder_yaw": 0.17578125,
      "right_shoulder_pitch": -71.54296875,
      "right_elbow_yaw": 0.087890625,
      "right_gripper": -0.17578125,
      "left_hip_yaw": -11.689453125,
      "left_hip_roll": 18.80859375,
      "left_hip_pitch": -40.517578125,
      "left_knee_pitch": 48.779296875,
      "left_ankle_pitch": 13.0078125,
      "right_hip_yaw": 9.140625,
      "right_hip_roll": 0.17578125,
      "right_hip_pitch": 26.455078125,
      "right_knee_pitch": -38.3203125,
      "right_ankle_pitch": -13.798828125
    },
    {
      "left_shoulder_yaw": -3.603515625,
      "left_shoulder_pitch": 78.75,
      "left_elbow_yaw": -0.263671875,
      "left_gripper": -0.087890625,
      "right_shoulder_yaw": 0.17578125,
      "right_shoulder_pitch": -70.6640625,
      "right_elbow_yaw": 0.087890625,
      "right_gripper": -0.17578125,
      "left_hip_yaw": -11.689453125,
      "left_hip_roll": 18.80859375,
      "left_hip_pitch": -40.4296875,
      "left_knee_pitch": 48.779296875,
      "left_ankle_pitch": 13.095703125,
      "right_hip_yaw": 9.052734375,
      "right_hip_roll": 0.17578125,
      "right_hip_pitch": 26.455078125,
      "right_knee_pitch": -38.671875,
      "right_ankle_pitch": -14.23828125
    },
    {
      "left_shoulder_yaw": -3.603515625,
      "left_shoulder_pitch": 78.75,
      "left_elbow_yaw": -0.263671875,
      "left_gripper": -0.087890625,
      "right_shoulder_yaw": 0.17578125,
      "right_shoulder_pitch": -70.751953125,
      "right_elbow_yaw": 0.087890625,
      "right_gripper": -0.17578125,
      "left_hip_yaw": -11.689453125,
      "left_hip_roll": 18.80859375,
      "left_hip_pitch": -40.4296875,
      "left_knee_pitch": 48.779296875,
      "left_ankle_pitch": 13.095703125,
      "right_hip_yaw": 8.7890625,
      "right_hip_roll": 0.17578125,
      "right_hip_pitch": 26.455078125,
      "right_knee_pitch": -38.759765625,
      "right_ankle_pitch": -14.23828125
    },
    {
      "left_shoulder_yaw": -3.603515625,
      "left_shoulder_pitch": 78.22265625,
      "left_elbow_yaw": -0.263671875,
      "left_gripper": -0.087890625,
      "right_shoulder_yaw": 0.17578125,
      "right_shoulder_pitch": -70.751953125,
      "right_elbow_yaw": 0.087890625,
      "right_gripper": -0.17578125,
      "left_hip_yaw": -11.689453125,
      "left_hip_roll": 18.80859375,
      "left_hip_pitch": -40.517578125,
      "left_knee_pitch": 49.130859375,
      "left_ankle_pitch": 13.095703125,
      "right_hip_yaw": 8.525390625,
      "right_hip_roll": 0.087890625,
      "right_hip_pitch": 26.630859375,
      "right_knee_pitch": -38.935546875,
      "right_ankle_pitch": -13.88671875
    },
    {
      "left_shoulder_yaw": -3.515625,
      "left_shoulder_pitch": 77.958984375,
      "left_elbow_yaw": -0.439453125,
      "left_gripper": -0.087890625,
      "right_shoulder_yaw": 0.17578125,
      "right_shoulder_pitch": -70.6640625,
      "right_elbow_yaw": 0.087890625,
      "right_gripper": -0.17578125,
      "left_hip_yaw": -11.689453125,
      "left_hip_roll": 18.80859375,
      "left_hip_pitch": -40.517578125,
      "left_knee_pitch": 49.482421875,
      "left_ankle_pitch": 13.095703125,
      "right_hip_yaw": 8.4375,
      "right_hip_roll": 0.087890625,
      "right_hip_pitch": 26.630859375,
      "right_knee_pitch": -39.0234375,
      "right_ankle_pitch": -13.798828125
    },
    {
      "left_shoulder_yaw": -3.515625,
      "left_shoulder_pitch": 77.87109375,
      "left_elbow_yaw": -0.439453125,
      "left_gripper": -0.087890625,
      "right_shoulder_yaw": 0.17578125,
      "right_shoulder_pitch": -70.576171875,
      "right_elbow_yaw": 0.087890625,
      "right_gripper": -0.17578125,
      "left_hip_yaw": -11.689453125,
      "left_hip_roll": 18.80859375,
      "left_hip_pitch": -39.990234375,
      "left_knee_pitch": 49.921875,
      "left_ankle_pitch": 13.095703125,
      "right_hip_yaw": 8.4375,
      "right_hip_roll": 0.087890625,
      "right_hip_pitch": 26.630859375,
      "right_knee_pitch": -39.0234375,
      "right_ankle_pitch": -14.4140625
    },
    {
      "left_shoulder_yaw": -3.515625,
      "left_shoulder_pitch": 77.87109375,
      "left_elbow_yaw": -0.615234375,
      "left_gripper": -0.087890625,
      "right_shoulder_yaw": 0.17578125,
      "right_shoulder_pitch": -70.576171875,
      "right_elbow_yaw": 0.087890625,
      "right_gripper": -0.17578125,
      "left_hip_yaw": -11.689453125,
      "left_hip_roll": 18.80859375,
      "left_hip_pitch": -39.638671875,
      "left_knee_pitch": 49.921875,
      "left_ankle_pitch": 13.095703125,
      "right_hip_yaw": 8.4375,
      "right_hip_roll": 0.087890625,
      "right_hip_pitch": 26.54296875,
      "right_knee_pitch": -38.935546875,
      "right_ankle_pitch": -14.58984375
    },
    {
      "left_shoulder_yaw": -3.515625,
      "left_shoulder_pitch": 77.87109375,
      "left_elbow_yaw": -0.703125,
      "left_gripper": -0.087890625,
      "right_shoulder_yaw": 0.17578125,
      "right_shoulder_pitch": -70.576171875,
      "right_elbow_yaw": 0.087890625,
      "right_gripper": -0.17578125,
      "left_hip_yaw": -11.689453125,
      "left_hip_roll": 18.80859375,
      "left_hip_pitch": -39.55078125,
      "left_knee_pitch": 49.921875,
      "left_ankle_pitch": 13.095703125,
      "right_hip_yaw": 8.4375,
      "right_hip_roll": 0.087890625,
      "right_hip_pitch": 26.455078125,
      "right_knee_pitch": -39.0234375,
      "right_ankle_pitch": -15.1171875
    },
    {
      "left_shoulder_yaw": -3.515625,
      "left_shoulder_pitch": 77.87109375,
      "left_elbow_yaw": -0.703125,
      "left_gripper": -0.087890625,
      "right_shoulder_yaw": 0.17578125,
      "right_shoulder_pitch": -70.6640625,
      "right_elbow_yaw": 0.087890625,
      "right_gripper": -0.17578125,
      "left_hip_yaw": -11.689453125,
      "left_hip_roll": 18.896484375,
      "left_hip_pitch": -39.55078125,
      "left_knee_pitch": 49.921875,
      "left_ankle_pitch": 13.095703125,
      "right_hip_yaw": 8.4375,
      "right_hip_roll": 0.087890625,
      "right_hip_pitch": 26.455078125,
      "right_knee_pitch": -39.111328125,
      "right_ankle_pitch": -15.1171875
    },
    {
      "left_shoulder_yaw": -3.515625,
      "left_shoulder_pitch": 78.134765625,
      "left_elbow_yaw": -0.703125,
      "left_gripper": -0.087890625,
      "right_shoulder_yaw": 0.17578125,
      "right_shoulder_pitch": -70.83984375,
      "right_elbow_yaw": 0.087890625,
      "right_gripper": -0.17578125,
      "left_hip_yaw": -11.689453125,
      "left_hip_roll": 18.896484375,
      "left_hip_pitch": -39.90234375,
      "left_knee_pitch": 49.921875,
      "left_ankle_pitch": 13.095703125,
      "right_hip_yaw": 8.4375,
      "right_hip_roll": 0.17578125,
      "right_hip_pitch": 26.54296875,
      "right_knee_pitch": -39.111328125,
      "right_ankle_pitch": -14.853515625
    },
    {
      "left_shoulder_yaw": -3.515625,
      "left_shoulder_pitch": 78.486328125,
      "left_elbow_yaw": -0.791015625,
      "left_gripper": -0.087890625,
      "right_shoulder_yaw": 0.17578125,
      "right_shoulder_pitch": -71.103515625,
      "right_elbow_yaw": 0.087890625,
      "right_gripper": -0.17578125,
      "left_hip_yaw": -11.689453125,
      "left_hip_roll": 18.896484375,
      "left_hip_pitch": -40.166015625,
      "left_knee_pitch": 49.921875,
      "left_ankle_pitch": 13.0078125,
      "right_hip_yaw": 8.525390625,
      "right_hip_roll": 0.3515625,
      "right_hip_pitch": 26.630859375,
      "right_knee_pitch": -38.671875,
      "right_ankle_pitch": -14.501953125
    },
    {
      "left_shoulder_yaw": -3.515625,
      "left_shoulder_pitch": 78.75,
      "left_elbow_yaw": -0.87890625,
      "left_gripper": -0.087890625,
      "right_shoulder_yaw": 0.17578125,
      "right_shoulder_pitch": -71.3671875,
      "right_elbow_yaw": 0.087890625,
      "right_gripper": -0.17578125,
      "left_hip_yaw": -11.689453125,
      "left_hip_roll": 18.896484375,
      "left_hip_pitch": -40.4296875,
      "left_knee_pitch": 49.921875,
      "left_ankle_pitch": 13.095703125,
      "right_hip_yaw": 8.525390625,
      "right_hip_roll": 0.3515625,
      "right_hip_pitch": 26.630859375,
      "right_knee_pitch": -38.056640625,
      "right_ankle_pitch": -14.326171875
    },
    {
      "left_shoulder_yaw": -3.515625,
      "left_shoulder_pitch": 78.75,
      "left_elbow_yaw": -1.142578125,
      "left_gripper": -0.087890625,
      "right_shoulder_yaw": 0.17578125,
      "right_shoulder_pitch": -71.455078125,
      "right_elbow_yaw": 0.087890625,
      "right_gripper": -0.17578125,
      "left_hip_yaw": -11.689453125,
      "left_hip_roll": 18.896484375,
      "left_hip_pitch": -40.517578125,
      "left_knee_pitch": 49.921875,
      "left_ankle_pitch": 13.18359375,
      "right_hip_yaw": 8.525390625,
      "right_hip_roll": 0.3515625,
      "right_hip_pitch": 26.630859375,
      "right_knee_pitch": -37.96875,
      "right_ankle_pitch": -14.326171875
    },
    {
      "left_shoulder_yaw": -3.515625,
      "left_shoulder_pitch": 78.75,
      "left_elbow_yaw": -1.142578125,
      "left_gripper": -0.087890625,
      "right_shoulder_yaw": 0.17578125,
      "right_shoulder_pitch": -71.455078125,
      "right_elbow_yaw": 0.087890625,
      "right_gripper": -0.17578125,
      "left_hip_yaw": -11.689453125,
      "left_hip_roll": 18.896484375,
      "left_hip_pitch": -40.517578125,
      "left_knee_pitch": 49.21875,
      "left_ankle_pitch": 13.18359375,
      "right_hip_yaw": 8.525390625,
      "right_hip_roll": 0.3515625,
      "right_hip_pitch": 26.630859375,
      "right_knee_pitch": -37.880859375,
      "right_ankle_pitch": -14.326171875
    },
    {
      "left_shoulder_yaw": -3.515625,
      "left_shoulder_pitch": 78.75,
      "left_elbow_yaw": -1.142578125,
      "left_gripper": -0.087890625,
      "right_shoulder_yaw": 0.17578125,
      "right_shoulder_pitch": -71.455078125,
      "right_elbow_yaw": 0.087890625,
      "right_gripper": -0.17578125,
      "left_hip_yaw": -11.689453125,
      "left_hip_roll": 18.896484375,
      "left_hip_pitch": -40.517578125,
      "left_knee_pitch": 48.8671875,
      "left_ankle_pitch": 13.18359375,
      "right_hip_yaw": 8.61328125,
      "right_hip_roll": 0.439453125,
      "right_hip_pitch": 26.630859375,
      "right_knee_pitch": -37.880859375,
      "right_ankle_pitch": -14.4140625
    },
    {
      "left_shoulder_yaw": -3.515625,
      "left_shoulder_pitch": 78.75,
      "left_elbow_yaw": -1.142578125,
      "left_gripper": -0.087890625,
      "right_shoulder_yaw": 0.17578125,
      "right_shoulder_pitch": -71.455078125,
      "right_elbow_yaw": 0.087890625,
      "right_gripper": -0.17578125,
      "left_hip_yaw": -11.689453125,
      "left_hip_roll": 18.896484375,
      "left_hip_pitch": -40.517578125,
      "left_knee_pitch": 48.779296875,
      "left_ankle_pitch": 13.18359375,
      "right_hip_yaw": 8.61328125,
      "right_hip_roll": 0.52734375,
      "right_hip_pitch": 26.630859375,
      "right_knee_pitch": -37.880859375,
      "right_ankle_pitch": -14.4140625
    },
    {
      "left_shoulder_yaw": -3.515625,
      "left_shoulder_pitch": 78.75,
      "left_elbow_yaw": -1.142578125,
      "left_gripper": -0.087890625,
      "right_shoulder_yaw": 0.17578125,
      "right_shoulder_pitch": -71.455078125,
      "right_elbow_yaw": 0.087890625,
      "right_gripper": -0.17578125,
      "left_hip_yaw": -11.689453125,
      "left_hip_roll": 18.896484375,
      "left_hip_pitch": -40.60546875,
      "left_knee_pitch": 48.779296875,
      "left_ankle_pitch": 13.271484375,
      "right_hip_yaw": 8.61328125,
      "right_hip_roll": 0.52734375,
      "right_hip_pitch": 26.71875,
      "right_knee_pitch": -37.79296875,
      "right_ankle_pitch": -14.4140625
    },
    {
      "left_shoulder_yaw": -3.515625,
      "left_shoulder_pitch": 78.486328125,
      "left_elbow_yaw": -0.87890625,
      "left_gripper": -0.087890625,
      "right_shoulder_yaw": 0.17578125,
      "right_shoulder_pitch": -71.3671875,
      "right_elbow_yaw": 0.087890625,
      "right_gripper": -0.17578125,
      "left_hip_yaw": -11.689453125,
      "left_hip_roll": 18.896484375,
      "left_hip_pitch": -40.60546875,
      "left_knee_pitch": 48.779296875,
      "left_ankle_pitch": 13.271484375,
      "right_hip_yaw": 8.61328125,
      "right_hip_roll": 0.52734375,
      "right_hip_pitch": 26.71875,
      "right_knee_pitch": -37.79296875,
      "right_ankle_pitch": -14.4140625
    },
    {
      "left_shoulder_yaw": -3.515625,
      "left_shoulder_pitch": 78.134765625,
      "left_elbow_yaw": -0.87890625,
      "left_gripper": -0.087890625,
      "right_shoulder_yaw": 0.17578125,
      "right_shoulder_pitch": -70.83984375,
      "right_elbow_yaw": 0.087890625,
      "right_gripper": -0.17578125,
      "left_hip_yaw": -11.689453125,
      "left_hip_roll": 18.984375,
      "left_hip_pitch": -40.60546875,
      "left_knee_pitch": 48.779296875,
      "left_ankle_pitch": 13.271484375,
      "right_hip_yaw": 8.61328125,
      "right_hip_roll": 0.52734375,
      "right_hip_pitch": 26.71875,
      "right_knee_pitch": -37.79296875,
      "right_ankle_pitch": -14.4140625
    },
    {
      "left_shoulder_yaw": -3.515625,
      "left_shoulder_pitch": 77.958984375,
      "left_elbow_yaw": -0.87890625,
      "left_gripper": -0.087890625,
      "right_shoulder_yaw": 0.17578125,
      "right_shoulder_pitch": -70.6640625,
      "right_elbow_yaw": 0.087890625,
      "right_gripper": -0.17578125,
      "left_hip_yaw": -11.689453125,
      "left_hip_roll": 18.984375,
      "left_hip_pitch": -40.60546875,
      "left_knee_pitch": 48.779296875,
      "left_ankle_pitch": 13.271484375,
      "right_hip_yaw": 8.61328125,
      "right_hip_roll": 0.52734375,
      "right_hip_pitch": 26.89453125,
      "right_knee_pitch": -37.96875,
      "right_ankle_pitch": -14.4140625
    },
    {
      "left_shoulder_yaw": -3.515625,
      "left_shoulder_pitch": 77.958984375,
      "left_elbow_yaw": -0.87890625,
      "left_gripper": -0.087890625,
      "right_shoulder_yaw": 0.17578125,
      "right_shoulder_pitch": -70.6640625,
      "right_elbow_yaw": 0.087890625,
      "right_gripper": -0.17578125,
      "left_hip_yaw": -11.689453125,
      "left_hip_roll": 18.984375,
      "left_hip_pitch": -40.60546875,
      "left_knee_pitch": 48.779296875,
      "left_ankle_pitch": 13.271484375,
      "right_hip_yaw": 8.61328125,
      "right_hip_roll": 0.52734375,
      "right_hip_pitch": 27.0703125,
      "right_knee_pitch": -37.96875,
      "right_ankle_pitch": -14.4140625
    },
    {
      "left_shoulder_yaw": -3.515625,
      "left_shoulder_pitch": 77.958984375,
      "left_elbow_yaw": -0.87890625,
      "left_gripper": -0.087890625,
      "right_shoulder_yaw": 0.17578125,
      "right_shoulder_pitch": -70.6640625,
      "right_elbow_yaw": 0.087890625,
      "right_gripper": -0.17578125,
      "left_hip_yaw": -11.689453125,
      "left_hip_roll": 18.984375,
      "left_hip_pitch": -40.60546875,
      "left_knee_pitch": 48.779296875,
      "left_ankle_pitch": 13.271484375,
      "right_hip_yaw": 8.61328125,
      "right_hip_roll": 0.52734375,
      "right_hip_pitch": 26.806640625,
      "right_knee_pitch": -37.96875,
      "right_ankle_pitch": -14.4140625
    },
    {
      "left_shoulder_yaw": -3.515625,
      "left_shoulder_pitch": 77.958984375,
      "left_elbow_yaw": -0.87890625,
      "left_gripper": -0.087890625,
      "right_shoulder_yaw": 0.17578125,
      "right_shoulder_pitch": -70.6640625,
      "right_elbow_yaw": 0.087890625,
      "right_gripper": -0.17578125,
      "left_hip_yaw": -11.689453125,
      "left_hip_roll": 18.984375,
      "left_hip_pitch": -40.60546875,
      "left_knee_pitch": 48.779296875,
      "left_ankle_pitch": 13.271484375,
      "right_hip_yaw": 8.61328125,
      "right_hip_roll": 0.439453125,
      "right_hip_pitch": 26.806640625,
      "right_knee_pitch": -38.056640625,
      "right_ankle_pitch": -14.4140625
    },
    {
      "left_shoulder_yaw": -3.515625,
      "left_shoulder_pitch": 77.958984375,
      "left_elbow_yaw": -0.87890625,
      "left_gripper": -0.087890625,
      "right_shoulder_yaw": 0.17578125,
      "right_shoulder_pitch": -70.6640625,
      "right_elbow_yaw": 0.087890625,
      "right_gripper": -0.17578125,
      "left_hip_yaw": -11.689453125,
      "left_hip_roll": 18.896484375,
      "left_hip_pitch": -40.693359375,
      "left_knee_pitch": 48.779296875,
      "left_ankle_pitch": 13.271484375,
      "right_hip_yaw": 8.61328125,
      "right_hip_roll": 0.439453125,
      "right_hip_pitch": 26.806640625,
      "right_knee_pitch": -38.14453125,
      "right_ankle_pitch": -14.4140625
    },
    {
      "left_shoulder_yaw": -3.515625,
      "left_shoulder_pitch": 77.958984375,
      "left_elbow_yaw": -0.791015625,
      "left_gripper": -0.087890625,
      "right_shoulder_yaw": 0.17578125,
      "right_shoulder_pitch": -70.6640625,
      "right_elbow_yaw": 0.087890625,
      "right_gripper": -0.17578125,
      "left_hip_yaw": -11.689453125,
      "left_hip_roll": 18.896484375,
      "left_hip_pitch": -40.693359375,
      "left_knee_pitch": 48.779296875,
      "left_ankle_pitch": 13.271484375,
      "right_hip_yaw": 8.61328125,
      "right_hip_roll": 0.439453125,
      "right_hip_pitch": 26.806640625,
      "right_knee_pitch": -38.14453125,
      "right_ankle_pitch": -14.4140625
    },
    {
      "left_shoulder_yaw": -3.515625,
      "left_shoulder_pitch": 77.958984375,
      "left_elbow_yaw": -0.615234375,
      "left_gripper": -0.087890625,
      "right_shoulder_yaw": 0.17578125,
      "right_shoulder_pitch": -70.6640625,
      "right_elbow_yaw": 0.087890625,
      "right_gripper": -0.17578125,
      "left_hip_yaw": -11.689453125,
      "left_hip_roll": 18.896484375,
      "left_hip_pitch": -40.693359375,
      "left_knee_pitch": 48.779296875,
      "left_ankle_pitch": 13.271484375,
      "right_hip_yaw": 8.61328125,
      "right_hip_roll": 0.439453125,
      "right_hip_pitch": 26.806640625,
      "right_knee_pitch": -38.14453125,
      "right_ankle_pitch": -14.501953125
    },
    {
      "left_shoulder_yaw": -3.515625,
      "left_shoulder_pitch": 77.958984375,
      "left_elbow_yaw": -0.52734375,
      "left_gripper": -0.087890625,
      "right_shoulder_yaw": 0.17578125,
      "right_shoulder_pitch": -70.6640625,
      "right_elbow_yaw": 0.087890625,
      "right_gripper": -0.17578125,
      "left_hip_yaw": -11.689453125,
      "left_hip_roll": 18.896484375,
      "left_hip_pitch": -40.693359375,
      "left_knee_pitch": 48.779296875,
      "left_ankle_pitch": 13.271484375,
      "right_hip_yaw": 8.61328125,
      "right_hip_roll": 0.439453125,
      "right_hip_pitch": 26.806640625,
      "right_knee_pitch": -38.14453125,
      "right_ankle_pitch": -14.501953125
    },
    {
      "left_shoulder_yaw": -3.515625,
      "left_shoulder_pitch": 77.958984375,
      "left_elbow_yaw": -0.3515625,
      "left_gripper": -0.087890625,
      "right_shoulder_yaw": 0.17578125,
      "right_shoulder_pitch": -70.576171875,
      "right_elbow_yaw": 0.087890625,
      "right_gripper": -0.17578125,
      "left_hip_yaw": -11.689453125,
      "left_hip_roll": 18.896484375,
      "left_hip_pitch": -40.693359375,
      "left_knee_pitch": 48.779296875,
      "left_ankle_pitch": 13.271484375,
      "right_hip_yaw": 8.61328125,
      "right_hip_roll": 0.439453125,
      "right_hip_pitch": 26.806640625,
      "right_knee_pitch": -38.14453125,
      "right_ankle_pitch": -14.501953125
    },
    {
      "left_shoulder_yaw": -3.515625,
      "left_shoulder_pitch": 77.87109375,
      "left_elbow_yaw": -0.087890625,
      "left_gripper": -0.087890625,
      "right_shoulder_yaw": 0.17578125,
      "right_shoulder_pitch": -70.576171875,
      "right_elbow_yaw": 0.087890625,
      "right_gripper": -0.17578125,
      "left_hip_yaw": -11.689453125,
      "left_hip_roll": 18.896484375,
      "left_hip_pitch": -40.693359375,
      "left_knee_pitch": 48.779296875,
      "left_ankle_pitch": 13.271484375,
      "right_hip_yaw": 8.61328125,
      "right_hip_roll": 0.439453125,
      "right_hip_pitch": 26.806640625,
      "right_knee_pitch": -38.3203125,
      "right_ankle_pitch": -14.4140625
    },
    {
      "left_shoulder_yaw": -3.515625,
      "left_shoulder_pitch": 77.87109375,
      "left_elbow_yaw": -0.087890625,
      "left_gripper": -0.087890625,
      "right_shoulder_yaw": 0.17578125,
      "right_shoulder_pitch": -70.576171875,
      "right_elbow_yaw": 0.087890625,
      "right_gripper": -0.17578125,
      "left_hip_yaw": -11.689453125,
      "left_hip_roll": 18.896484375,
      "left_hip_pitch": -40.693359375,
      "left_knee_pitch": 48.779296875,
      "left_ankle_pitch": 13.271484375,
      "right_hip_yaw": 8.61328125,
      "right_hip_roll": 0.439453125,
      "right_hip_pitch": 26.806640625,
      "right_knee_pitch": -38.3203125,
      "right_ankle_pitch": -14.4140625
    },
    {
      "left_shoulder_yaw": -3.515625,
      "left_shoulder_pitch": 77.87109375,
      "left_elbow_yaw": -0.3515625,
      "left_gripper": -0.087890625,
      "right_shoulder_yaw": 0.17578125,
      "right_shoulder_pitch": -70.576171875,
      "right_elbow_yaw": 0.087890625,
      "right_gripper": -0.17578125,
      "left_hip_yaw": -11.689453125,
      "left_hip_roll": 18.896484375,
      "left_hip_pitch": -40.693359375,
      "left_knee_pitch": 48.779296875,
      "left_ankle_pitch": 13.271484375,
      "right_hip_yaw": 8.61328125,
      "right_hip_roll": 0.439453125,
      "right_hip_pitch": 26.806640625,
      "right_knee_pitch": -38.3203125,
      "right_ankle_pitch": -14.4140625
    },
    {
      "left_shoulder_yaw": -3.515625,
      "left_shoulder_pitch": 77.87109375,
      "left_elbow_yaw": -0.52734375,
      "left_gripper": -0.087890625,
      "right_shoulder_yaw": 0.17578125,
      "right_shoulder_pitch": -70.576171875,
      "right_elbow_yaw": 0.087890625,
      "right_gripper": -0.17578125,
      "left_hip_yaw": -11.689453125,
      "left_hip_roll": 18.896484375,
      "left_hip_pitch": -40.693359375,
      "left_knee_pitch": 48.779296875,
      "left_ankle_pitch": 13.271484375,
      "right_hip_yaw": 8.61328125,
      "right_hip_roll": 0.439453125,
      "right_hip_pitch": 26.806640625,
      "right_knee_pitch": -38.3203125,
      "right_ankle_pitch": -14.4140625
    },
    {
      "left_shoulder_yaw": -3.515625,
      "left_shoulder_pitch": 77.87109375,
      "left_elbow_yaw": -0.52734375,
      "left_gripper": -0.087890625,
      "right_shoulder_yaw": 0.17578125,
      "right_shoulder_pitch": -70.576171875,
      "right_elbow_yaw": 0.087890625,
      "right_gripper": -0.17578125,
      "left_hip_yaw": -11.689453125,
      "left_hip_roll": 18.896484375,
      "left_hip_pitch": -40.693359375,
      "left_knee_pitch": 48.779296875,
      "left_ankle_pitch": 13.271484375,
      "right_hip_yaw": 8.61328125,
      "right_hip_roll": 0.439453125,
      "right_hip_pitch": 26.806640625,
      "right_knee_pitch": -38.3203125,
      "right_ankle_pitch": -14.326171875
    },
    {
      "left_shoulder_yaw": -3.515625,
      "left_shoulder_pitch": 77.87109375,
      "left_elbow_yaw": -0.52734375,
      "left_gripper": -0.087890625,
      "right_shoulder_yaw": 0.17578125,
      "right_shoulder_pitch": -70.576171875,
      "right_elbow_yaw": 0.087890625,
      "right_gripper": -0.17578125,
      "left_hip_yaw": -11.689453125,
      "left_hip_roll": 18.80859375,
      "left_hip_pitch": -40.693359375,
      "left_knee_pitch": 48.779296875,
      "left_ankle_pitch": 13.271484375,
      "right_hip_yaw": 8.61328125,
      "right_hip_roll": 0.3515625,
      "right_hip_pitch": 26.806640625,
      "right_knee_pitch": -38.3203125,
      "right_ankle_pitch": -14.326171875
    },
    {
      "left_shoulder_yaw": -3.515625,
      "left_shoulder_pitch": 77.87109375,
      "left_elbow_yaw": -0.52734375,
      "left_gripper": -0.087890625,
      "right_shoulder_yaw": 0.17578125,
      "right_shoulder_pitch": -70.576171875,
      "right_elbow_yaw": 0.087890625,
      "right_gripper": -0.17578125,
      "left_hip_yaw": -11.689453125,
      "left_hip_roll": 18.80859375,
      "left_hip_pitch": -40.693359375,
      "left_knee_pitch": 48.779296875,
      "left_ankle_pitch": 13.271484375,
      "right_hip_yaw": 8.61328125,
      "right_hip_roll": 0.3515625,
      "right_hip_pitch": 26.71875,
      "right_knee_pitch": -38.3203125,
      "right_ankle_pitch": -14.326171875
    },
    {
      "left_shoulder_yaw": -3.515625,
      "left_shoulder_pitch": 77.87109375,
      "left_elbow_yaw": -0.52734375,
      "left_gripper": -0.087890625,
      "right_shoulder_yaw": 0.17578125,
      "right_shoulder_pitch": -70.576171875,
      "right_elbow_yaw": 0.087890625,
      "right_gripper": -0.17578125,
      "left_hip_yaw": -11.689453125,
      "left_hip_roll": 18.80859375,
      "left_hip_pitch": -40.693359375,
      "left_knee_pitch": 48.779296875,
      "left_ankle_pitch": 13.271484375,
      "right_hip_yaw": 8.61328125,
      "right_hip_roll": 0.3515625,
      "right_hip_pitch": 26.71875,
      "right_knee_pitch": -38.3203125,
      "right_ankle_pitch": -14.326171875
    }
  ]
}